mlbrecaps/__init__.py
mlbrecaps/broadcast.py
mlbrecaps/clip.py
mlbrecaps/date.py
mlbrecaps/game.py
mlbrecaps/game_play_ids.py
mlbrecaps/games.py
mlbrecaps/play.py
mlbrecaps/player.py
mlbrecaps/plays.py
mlbrecaps/team.py
mlbrecaps/utils.py
mlbrecaps-0.1.0.dist-info/licenses/LICENSE.md
mlbrecaps-0.1.0.dist-info/METADATA
mlbrecaps-0.1.0.dist-info/WHEEL
mlbrecaps-0.1.0.dist-info/top_level.txt
mlbrecaps-0.1.0.dist-info/RECORD
