Metadata-Version: 2.4
Name: mlbrecaps
Version: 0.1.0
Summary: Package that gathers information on given MLB games and allows downloading of video clips of plays.
Requires-Python: >=3.12
License-File: LICENSE.md
Requires-Dist: bs4>=0.0.2
Requires-Dist: curl-cffi>=0.13.0
Requires-Dist: fireducks>=1.3.3
Requires-Dist: lark>=1.2.2
Requires-Dist: lxml>=6.0.0
Requires-Dist: pydantic>=2.11.7
Requires-Dist: pyyaml>=6.0.2
Dynamic: license-file
